pretix_map-0.1.4.dist-info/licenses/LICENSE
pretix_mapplugin/__init__.py
pretix_mapplugin/apps.py
pretix_mapplugin/geocoding.py
pretix_mapplugin/models.py
pretix_mapplugin/signals.py
pretix_mapplugin/tasks.py
pretix_mapplugin/urls.py
pretix_mapplugin/views.py
pretix_mapplugin/locale/de/LC_MESSAGES/django.mo
pretix_mapplugin/locale/de/LC_MESSAGES/django.po
pretix_mapplugin/locale/de_Informal/.gitkeep
pretix_mapplugin/locale/de_Informal/LC_MESSAGES/django.mo
pretix_mapplugin/locale/de_Informal/LC_MESSAGES/django.po
pretix_mapplugin/management/__init__.py
pretix_mapplugin/management/commands/__init__.py
pretix_mapplugin/management/commands/geocode_existing_orders.py
pretix_mapplugin/migrations/0001_initial.py
pretix_mapplugin/migrations/0002_remove_ordergeocodedata_geocoded_timestamp_and_more.py
pretix_mapplugin/migrations/__init__.py
pretix_mapplugin/static/pretix_mapplugin/.gitkeep
pretix_mapplugin/static/pretix_mapplugin/css/salesmap.css
pretix_mapplugin/static/pretix_mapplugin/js/salesmap.js
pretix_mapplugin/static/pretix_mapplugin/libs/leaflet-sales-map/MarkerCluster.Default.css
pretix_mapplugin/static/pretix_mapplugin/libs/leaflet-sales-map/MarkerCluster.css
pretix_mapplugin/static/pretix_mapplugin/libs/leaflet-sales-map/leaflet-heat.js
pretix_mapplugin/static/pretix_mapplugin/libs/leaflet-sales-map/leaflet-src.esm.js
pretix_mapplugin/static/pretix_mapplugin/libs/leaflet-sales-map/leaflet-src.esm.js.map
pretix_mapplugin/static/pretix_mapplugin/libs/leaflet-sales-map/leaflet-src.js
pretix_mapplugin/static/pretix_mapplugin/libs/leaflet-sales-map/leaflet-src.js.map
pretix_mapplugin/static/pretix_mapplugin/libs/leaflet-sales-map/leaflet.css
pretix_mapplugin/static/pretix_mapplugin/libs/leaflet-sales-map/leaflet.js
pretix_mapplugin/static/pretix_mapplugin/libs/leaflet-sales-map/leaflet.js.map
pretix_mapplugin/static/pretix_mapplugin/libs/leaflet-sales-map/leaflet.markercluster.js
pretix_mapplugin/static/pretix_mapplugin/libs/leaflet-sales-map/leaflet.markercluster.js.map
pretix_map-0.1.4.dist-info/METADATA
pretix_map-0.1.4.dist-info/WHEEL
pretix_map-0.1.4.dist-info/entry_points.txt
pretix_map-0.1.4.dist-info/top_level.txt
pretix_map-0.1.4.dist-info/RECORD
