Metadata-Version: 2.4
Name: pretix-map
Version: 0.1.4
Summary: An overview map of the catchment area of previous orders. Measured by postcode
Author-email: MarkenJaden <jjsch1410@gmail.com>
Maintainer-email: MarkenJaden <jjsch1410@gmail.com>
License: Apache
Project-URL: homepage, https://github.com/MarkenJaden/pretix-map
Project-URL: repository, https://github.com/MarkenJaden/pretix-map
Keywords: pretix
License-File: LICENSE
Requires-Dist: geopy
Dynamic: license-file
